firstPKG/__init__.py
firstPKG/request.py
firstPKG/test.txt
first_pkg_joeyding-0.0.2.dist-info/METADATA
first_pkg_joeyding-0.0.2.dist-info/WHEEL
first_pkg_joeyding-0.0.2.dist-info/top_level.txt
first_pkg_joeyding-0.0.2.dist-info/RECORD
