Metadata-Version: 2.1
Name: first-pkg-joeyding
Version: 0.0.2
Summary: A small example package
Author: Joeyding
Author-email: joeyding@tencent.com
Classifier: Programming Language :: Python :: 3
Classifier: License :: OSI Approved :: MIT License
Classifier: Operating System :: OS Independent
Requires-Python: >=3.6
Requires-Dist: requests (>=2.0)
